docs/conf.py
google/identity/accesscontextmanager/type/__init__.py
google/identity/accesscontextmanager/type/device_resources.proto
google/identity/accesscontextmanager/type/device_resources_pb2.py
google/identity/accesscontextmanager/type/device_resources_pb2.pyi
google/identity/accesscontextmanager/v1/__init__.py
google/identity/accesscontextmanager/v1/access_context_manager.proto
google/identity/accesscontextmanager/v1/access_context_manager_pb2.py
google/identity/accesscontextmanager/v1/access_context_manager_pb2.pyi
google/identity/accesscontextmanager/v1/access_level.proto
google/identity/accesscontextmanager/v1/access_level_pb2.py
google/identity/accesscontextmanager/v1/access_level_pb2.pyi
google/identity/accesscontextmanager/v1/access_policy.proto
google/identity/accesscontextmanager/v1/access_policy_pb2.py
google/identity/accesscontextmanager/v1/access_policy_pb2.pyi
google/identity/accesscontextmanager/v1/gcp_user_access_binding.proto
google/identity/accesscontextmanager/v1/gcp_user_access_binding_pb2.py
google/identity/accesscontextmanager/v1/gcp_user_access_binding_pb2.pyi
google/identity/accesscontextmanager/v1/service_perimeter.proto
google/identity/accesscontextmanager/v1/service_perimeter_pb2.py
google/identity/accesscontextmanager/v1/service_perimeter_pb2.pyi
google_cloud_access_context_manager-0.2.3.dist-info/licenses/LICENSE
google_cloud_access_context_manager-0.2.3.dist-info/METADATA
google_cloud_access_context_manager-0.2.3.dist-info/WHEEL
google_cloud_access_context_manager-0.2.3.dist-info/top_level.txt
google_cloud_access_context_manager-0.2.3.dist-info/RECORD
